pyriodic_table/__init__.py
pyriodic_table/chemelements.py
pyriodic_table/data.py
pyriodic_table/exceptions.py
pyriodic_table/periodictable.py
pyriodic_table-1.0.1.dist-info/LICENSE
pyriodic_table-1.0.1.dist-info/METADATA
pyriodic_table-1.0.1.dist-info/WHEEL
pyriodic_table-1.0.1.dist-info/top_level.txt
pyriodic_table-1.0.1.dist-info/RECORD
