Metadata-Version: 2.1
Name: pyriodic-table
Version: 1.0.1
Summary: A package which provides data on the Periodic Table of Elements.
Author-email: Leo Zhang <leozhang0214@gmail.com>
License: MIT License        
Project-URL: Homepage, https://github.com/leoz0214/pyriodic-table
Project-URL: Bug Tracker, https://github.com/leoz0214/pyriodic-table/issues
Classifier: Programming Language :: Python :: 3
Classifier: Operating System :: OS Independent
Requires-Python: >=3.9
License-File: LICENSE
